Accern-0.4.0.dist-info/DESCRIPTION.rst
Accern-0.4.0.dist-info/LICENSE.txt
Accern-0.4.0.dist-info/METADATA
Accern-0.4.0.dist-info/RECORD
Accern-0.4.0.dist-info/WHEEL
Accern-0.4.0.dist-info/metadata.json
Accern-0.4.0.dist-info/top_level.txt
accern/__init__.py
accern/api.py
accern/config.py
accern/default_client.py
accern/error.py
accern/historical.py
accern/schema.py
accern/stream.py
accern/util.py
accern/version.py
accern/data/options.json
