Metadata-Version: 2.0
Name: Accern
Version: 0.4.0
Summary: A python library for Accern Data API
Home-page: https://github.com/Accern/accern-python
Author: UNKNOWN
Author-email: UNKNOWN
License: MIT License
Platform: Posix; MacOS X; Windows
Classifier: Development Status :: 4 - Beta
Classifier: Intended Audience :: Developers
Classifier: Intended Audience :: Financial and Insurance Industry
Classifier: Topic :: Office/Business :: Financial :: Investment
Classifier: License :: OSI Approved :: MIT License
Classifier: Operating System :: OS Independent
Classifier: Programming Language :: Python
Classifier: Programming Language :: Python :: 2
Classifier: Programming Language :: Python :: 2.7
Classifier: Programming Language :: Python :: 3.6
Requires-Dist: requests (>=2.20.0)
Requires-Dist: six (>=1.10.0)
